aloha_data_collection/__init__.py
aloha_data_collection/__main__.py
aloha_data_collection/configs/calibration/aloha_default/left_follower.json
aloha_data_collection/configs/calibration/aloha_default/left_leader.json
aloha_data_collection/configs/calibration/aloha_default/right_follower.json
aloha_data_collection/configs/calibration/aloha_default/right_leader.json
aloha_data_collection/configs/robot/aloha.yaml
aloha_data_collection/configs/tasks.yaml
aloha_data_collection/post_install.py
aloha_data_collection/resources/__init__.py
aloha_data_collection/resources/aloha.png
aloha_data_collection/resources/app.py
aloha_data_collection/resources/app.ui
aloha_data_collection/resources/no_video.jpg
aloha_data_collection/run_mdc.sh
aloha_data_collection/ui/__init__.py
aloha_data_collection/ui/main_window.py
aloha_data_collection/utils/__init__.py
aloha_data_collection/utils/constants.py
aloha_data_collection/utils/utils.py
aloha_data_collection/workers/__init__.py
aloha_data_collection/workers/recorder.py
aloha_data_collection/workers/yaml.py
aloha_data_collection-0.1.16.dist-info/METADATA
aloha_data_collection-0.1.16.dist-info/WHEEL
aloha_data_collection-0.1.16.dist-info/entry_points.txt
aloha_data_collection-0.1.16.dist-info/RECORD
